.editorconfig
.gitignore
.readthedocs.yml
AUTHORS.rst
CODE_OF_CONDUCT.rst
CONTRIBUTING.rst
HISTORY.rst
LICENSE
MANIFEST.in
Makefile
README.rst
pss_logo.jpg
requirements.txt
requirements_dev.txt
setup.cfg
setup.py
.github/workflows/ci_test.yml
data/B1855+09.L-wide.PUPPI.11y.x.sum.sm
data/J1713+0747_NANOGrav_11yv1.gls.par
data/J1910+1256_NANOGrav_11yv1.gls.par
data/test.fits
data/test_parfile.par
data/txt_search_test.txt
docs/.gitignore
docs/Makefile
docs/authors.rst
docs/code_of_conduct.rst
docs/conf.py
docs/contributing.rst
docs/history.rst
docs/index.rst
docs/installation.rst
docs/ism_options_tutorial_4.rst
docs/make.bat
docs/modules.rst
docs/nb-rst.tpl
docs/pulse_nulling_example.rst
docs/pulse_profiles_tutorial_3.rst
docs/readme.rst
docs/requirements.txt
docs/simulate_tutorial.rst
docs/telescopes_tutorial_5.rst
docs/tutorial_1.rst
docs/tutorial_2.rst
docs/_build/html/_images/Pulse_Nulling_Example_13_0.png
docs/_build/html/_images/Pulse_Nulling_Example_15_1.png
docs/_build/html/_images/Pulse_Nulling_Example_18_0.png
docs/_build/html/_images/Pulse_Nulling_Example_20_1.png
docs/_build/html/_images/Simulate_Tutorial_10_0.png
docs/_build/html/_images/Simulate_Tutorial_10_1.png
docs/_build/html/_images/Simulate_Tutorial_14_0.png
docs/_build/html/_images/Simulate_Tutorial_14_1.png
docs/_build/html/_images/Simulate_Tutorial_14_2.png
docs/_build/html/_images/Simulate_Tutorial_9_0.png
docs/_build/html/_images/full_pipeline_tutorial_10_1.png
docs/_build/html/_images/full_pipeline_tutorial_17_0.png
docs/_build/html/_images/full_pipeline_tutorial_17_1.png
docs/_build/html/_images/full_pipeline_tutorial_19_1.png
docs/_build/html/_images/full_pipeline_tutorial_21_0.png
docs/_build/html/_images/full_pipeline_tutorial_29_0.png
docs/_build/html/_images/full_pipeline_tutorial_31_1.png
docs/_build/html/_images/full_pipeline_tutorial_32_0.png
docs/_build/html/_images/full_pipeline_tutorial_36_1.png
docs/_build/html/_images/full_pipeline_tutorial_36_3.png
psrsigsim.egg-info/PKG-INFO
psrsigsim.egg-info/SOURCES.txt
psrsigsim.egg-info/dependency_links.txt
psrsigsim.egg-info/not-zip-safe
psrsigsim.egg-info/requires.txt
psrsigsim.egg-info/top_level.txt
