Metadata-Version: 1.1
Name: psrsigsim
Version: 1.0.1
Summary: The NANOGrav Pulsar Signal Simulator.
Home-page: https://github.com/PsrSigSim/PsrSigSim
Author: Jeffrey S. Hazboun
Author-email: jeffrey.hazboun@nanograv.org
License: MIT license
Keywords: psrsigsim
Platform: UNKNOWN
Classifier: Development Status :: 2 - Pre-Alpha
Classifier: Intended Audience :: Developers
Classifier: License :: OSI Approved :: MIT License
Classifier: Natural Language :: English
Classifier: Programming Language :: Python :: 3
Classifier: Programming Language :: Python :: 3.6
Classifier: Programming Language :: Python :: 3.7
Classifier: Programming Language :: Python :: 3.8
